{
    "projectname": "cornel_website",
    "setting": {
        "compileHotReLoad": true,
        "urlCheck": false
    },
    "description": "Project configuration file, more information: https://developers.weixin.qq.com/miniprogram/dev/devtools/projectconfig.html",
    "condition": {
        "miniprogram": {
            "list": [
                {
                    "name": "follow",
                    "pathName": "pages/follow/index",
                    "query": "",
                    "launchMode": "default",
                    "scene": null
                }
            ]
        }
    }
}